mongoblack/__init__.py
mongoblack-1.0.4.dist-info/LICENSE
mongoblack-1.0.4.dist-info/METADATA
mongoblack-1.0.4.dist-info/WHEEL
mongoblack-1.0.4.dist-info/top_level.txt
mongoblack-1.0.4.dist-info/RECORD
