Metadata-Version: 2.1
Name: mongoblack
Version: 1.0.4
Summary: MongoDB handlers to streamline application interfaces
Home-page: https://github.com/BlackburnHax/mongoblack
Author: Brandon Blackburn
Author-email: contact@bhax.net
License: Apache 2.0
Platform: UNKNOWN
Classifier: License :: OSI Approved :: Apache Software License
Classifier: Operating System :: MacOS :: MacOS X
Classifier: Operating System :: Microsoft :: Windows
Classifier: Operating System :: POSIX
Classifier: Programming Language :: Python
Classifier: Programming Language :: Python :: 3
Classifier: Programming Language :: Python :: 3 :: Only
Classifier: Natural Language :: English
Classifier: Topic :: Text Processing :: Markup :: reStructuredText
Classifier: Topic :: Database :: Database Engines/Servers
License-File: LICENSE
Requires-Dist: pymongo
